{"cameraMode":{"drawMode":0,"name":"Shaded","section":"Shading Mode"},"sceneLighting":true,"audioPlay":false,"sceneViewState":{"m_AlwaysRefresh":false,"showFog":true,"showSkybox":true,"showFlares":true,"showImageEffects":true,"showParticleSystems":true,"showVisualEffectGraphs":true,"m_FxEnabled":true},"in2DMode":false,"pivot":{"x":35.185279846191409,"y":5.399232864379883,"z":-9.181650161743164},"rotation":{"x":0.12531200051307679,"y":-0.7730377316474915,"z":0.16144797205924989,"w":0.6006426811218262},"size":2.414635419845581,"orthographic":false}